{
  "5492": true,
  "5495": true,
  "5497": true,
  "5501": true,
  "5504": true,
  "5509": true,
  "5513": true,
  "5514": true,
  "5518": true,
  "5520": true,
  "5526": true,
  "5529": true,
  "5532": true,
  "5535": true,
  "5538": true,
  "5542": true,
  "5545": true,
  "5550": true,
  "5553": true,
  "5554": true,
  "5559": true,
  "5562": true,
  "5567": true,
  "5570": true,
  "5576": true,
  "6489": true,
  "6491": true,
  "6497": true,
  "6500": true,
  "6502": true,
  "6505": true,
  "6508": true,
  "34328": true,
  "34331": true
}